uvtx/__init__.py
uvtx/__main__.py
uvtx/cli.py
uvtx/completion.py
uvtx/condition_evaluator.py
uvtx/config.py
uvtx/dotenv.py
uvtx/executor.py
uvtx/graph.py
uvtx/models.py
uvtx/parallel.py
uvtx/runner.py
uvtx/script_meta.py
uvtx/variables.py
uvtx/watch.py
uvtx/formatters/__init__.py
uvtx/formatters/graph.py
uvtx-0.3.1.dist-info/METADATA
uvtx-0.3.1.dist-info/WHEEL
uvtx-0.3.1.dist-info/entry_points.txt
uvtx-0.3.1.dist-info/licenses/LICENSE
uvtx-0.3.1.dist-info/RECORD
