Metadata-Version: 2.4
Name: uvtx
Version: 0.3.1
Summary: A modern Python task runner built for uv with profiles, inheritance, and PEP 723 support
Project-URL: Homepage, https://github.com/mikeleppane/uvtx
Project-URL: Repository, https://github.com/mikeleppane/uvtx
Project-URL: Documentation, https://github.com/mikeleppane/uvtx#readme
Project-URL: Issue Tracker, https://github.com/mikeleppane/uvtx/issues
Project-URL: Changelog, https://github.com/mikeleppane/uvtx/releases
Author-email: mikelep <mleppan23@gmail.com>
License-Expression: MIT
License-File: LICENSE
Keywords: automation,build-automation,build-tool,cli,developer-tools,devops,python,runner,task,task-orchestration,task-runner,uv,workflow
Classifier: Development Status :: 3 - Alpha
Classifier: Environment :: Console
Classifier: Intended Audience :: Developers
Classifier: License :: OSI Approved :: MIT License
Classifier: Programming Language :: Python :: 3
Classifier: Programming Language :: Python :: 3.11
Classifier: Programming Language :: Python :: 3.12
Classifier: Programming Language :: Python :: 3.13
Classifier: Topic :: Software Development :: Build Tools
Classifier: Topic :: Utilities
Requires-Python: >=3.11
Requires-Dist: click>=8.0
Requires-Dist: pydantic>=2.0
Requires-Dist: rich>=13.0
